distimate/__init__.py
distimate/distributions.py
distimate/pandasext.py
distimate/stats.py
distimate/types.py
distimate-0.1.dist-info/LICENSE
distimate-0.1.dist-info/METADATA
distimate-0.1.dist-info/NOTICE
distimate-0.1.dist-info/WHEEL
distimate-0.1.dist-info/top_level.txt
distimate-0.1.dist-info/RECORD
