Metadata-Version: 2.1
Name: distimate
Version: 0.1
Summary: Distributions visualized
Home-page: https://github.com/akamai/distimate
Author: Miloslav Pojman
Author-email: mpojman@akamai.com
License: Apache License 2.0
Project-URL: Documentation, https://distimate.readthedocs.io/
Project-URL: Source Code, https://github.com/akamai/distimate
Keywords: statistics,plotting,histogram,distribution,CDF,PDF,quantile,percentile,Pandas,Matplotlib
Platform: UNKNOWN
Classifier: Framework :: IPython
Classifier: Framework :: Jupyter
Classifier: Framework :: Matplotlib
Classifier: Intended Audience :: Science/Research
Classifier: License :: OSI Approved :: Apache Software License
Classifier: Programming Language :: Python
Classifier: Programming Language :: Python :: 3
Classifier: Programming Language :: Python :: 3.6
Classifier: Programming Language :: Python :: 3.7
Classifier: Programming Language :: Python :: 3.8
Classifier: Topic :: Scientific/Engineering
Classifier: Topic :: Scientific/Engineering :: Information Analysis
Classifier: Topic :: Scientific/Engineering :: Mathematics
Classifier: Topic :: Scientific/Engineering :: Visualization
Classifier: Topic :: Software Development :: Libraries
Classifier: Topic :: Software Development :: Libraries :: Python Modules
Requires-Python: >=3.6
Requires-Dist: numpy
Provides-Extra: dev
Requires-Dist: flake8 ; extra == 'dev'
Requires-Dist: pytest ; extra == 'dev'
Provides-Extra: pandas
Requires-Dist: pandas (>=1.0.0) ; extra == 'pandas'
